Metadata-Version: 2.1
Name: data-formatada
Version: 1.0
Summary: Pacote para trabalhar com datas e horas no Brasil
Author: Mauricio Benjamin da Rocha & Pedro Antonio Vital de Sousa Carvalho
Author-email: mauriciobenjamin700@gmail.com
License: MIT License
Keywords: datas tempo
License-File: LICENCE
